Workbook

Sheet Cover
A2: Financial Statement Analysis
A3: HCL Technologies Ltd. vs Wipro Ltd.
B5: Team Members: | C5: K P Manoj (2025MB26539)
C6: T Venkata Suresh (2025MB26590)
C7: Japleen Kaur Khorana (2025MB26602)
C8: Varsha PS (2025MB26503)
C9: Prashanth G (2025MB26598)
B10: Course: | C10: Financial Management & Accounting
B11: Programme: | C11: MBA in AI for Business
B12: Institution: | C12: BITS Pilani (WILP)
B13: Semester: | C13: 1 - Batch Jan 2026
B14: Period of Analysis: | C14: FY2021 to FY2025
B15: Data Source: | C15: Moneycontrol (Consolidated Statements)

Sheet HCL_Data
A1: HCL Technologies - Consolidated Financial Data (Rs Cr)
A3: BALANCE SHEET
A4: Particulars | B4: FY2025 | C4: FY2024 | D4: FY2023 | E4: FY2022 | F4: FY2021
A5: EQUITIES AND LIABILITIES
A6: SHAREHOLDER'S FUNDS
A7: Equity Share Capital | B7: 543 | C7: 543 | D7: 543 | E7: 543 | F7: 543
A8: Total Share Capital | B8: 543 | C8: 543 | D8: 543 | E8: 543 | F8: 543
A9: Reserves and Surplus | B9: 69112 | C9: 67720 | D9: 64862 | E9: 61371 | F9: 59370
A10: Total Reserves and Surplus | B10: 69112 | C10: 67720 | D10: 64862 | E10: 61371 | F10: 59370
A11: Total Shareholders Funds | B11: 69655 | C11: 68263 | D11: 65405 | E11: 61914 | F11: 59913
A12: Minority Interest | B12: 18 | C12: 8 | D12: -7 | E12: 92 | F12: 169
A13: NON-CURRENT LIABILITIES
A14: Long Term Borrowings | B14: 70 | C14: 2223 | D14: 2111 | E14: 3923 | F14: 3828
A15: Deferred Tax Liabilities [Net] | B15: 1615 | C15: 771 | D15: 161 | E15: 112 | F15: 147
A16: Other Long Term Liabilities | B16: 4227 | C16: 4174 | D16: 2995 | E16: 2802 | F16: 3421
A17: Long Term Provisions | B17: 1920 | C17: 1612 | D17: 1315 | E17: 1415 | F17: 1333
A18: Total Non-Current Liabilities | B18: 7832 | C18: 8780 | D18: 6582 | E18: 8252 | F18: 8729
A19: CURRENT LIABILITIES
A20: Short Term Borrowings | B20: 2221 | C20: 104 | D20: 140 | E20: 62 | F20: 0
A21: Trade Payables | B21: 13234 | C21: 5853 | D21: 6428 | E21: 6278 | F21: 1726 | G21: 1166
A22: Other Current Liabilities | B22: 11097 | C22: 15432 | D22: 13743 | E22: 11480 | F22: 14694
A23: Short Term Provisions | B23: 1487 | C23: 1337 | D23: 1120 | E23: 955 | F23: 963
A24: Total Current Liabilities | B24: 28039 | C24: 22726 | D24: 21431 | E24: 18775 | F24: 17383
A25: Total Capital And Liabilities | B25: 105544 | C25: 99777 | D25: 93411 | E25: 89033 | F25: 86194
A26: ASSETS
A27: NON-CURRENT ASSETS
A28: Tangible Assets | B28: 7517 | C28: 7801 | D28: 7708 | E28: 7917 | F28: 8052
A29: Intangible Assets | B29: 6899 | C29: 7130 | D29: 8344 | E29: 9743 | F29: 11901
A30: Capital Work-In-Progress | B30: 59 | C30: 108 | D30: 40 | E30: 129 | F30: 312
A31: Fixed Assets | B31: 14475 | C31: 15039 | D31: 16092 | E31: 17789 | F31: 20265
A32: Non-Current Investments | B32: 91 | C32: 94 | D32: 110 | E32: 112 | F32: 89
A33: Deferred Tax Assets [Net] | B33: 1064 | C33: 1031 | D33: 1252 | E33: 1176 | F33: 1181
A34: Long Term Loans And Advances | B34: 586 | C34: 286 | D34: 0 | E34: 200 | F34: 0
A35: Other Non-Current Assets | B35: 5463 | C35: 3864 | D35: 3813 | E35: 4298 | F35: 4416
A36: Total Non-Current Assets | B36: 43435 | C36: 40446 | D36: 39834 | E36: 40992 | F36: 43143
A37: CURRENT ASSETS
A38: Current Investments | B38: 7473 | C38: 7043 | D38: 5385 | E38: 6239 | F38: 6773
A39: Inventories | B39: 133 | C39: 185 | D39: 228 | E39: 161 | F39: 94 | G39: 91
A40: Trade Receivables | B40: 25842 | C40: 25521 | D40: 25506 | E40: 20671 | F40: 13663 | G40: 14131
A41: Cash And Cash Equivalents | B41: 21289 | C41: 20150 | D41: 14724 | E41: 12636 | F41: 8888
A42: Short Term Loans And Advances | B42: 976 | C42: 795 | D42: 2603 | E42: 3008 | F42: 4841
A43: OtherCurrentAssets | B43: 6396 | C43: 5637 | D43: 5131 | E43: 5326 | F43: 8792
A44: Total Current Assets | B44: 62109 | C44: 59331 | D44: 53577 | E44: 48041 | F44: 43051
A45: Total Assets | B45: 105544 | C45: 99777 | D45: 93411 | E45: 89033 | F45: 86194
A46: OTHER ADDITIONAL INFORMATION
A47: CONTINGENT LIABILITIES, COMMITMENTS
A48: Contingent Liabilities | B48: 611 | C48: 135 | D48: 233 | E48: 892 | F48: 490
A49: BONUS DETAILS
A50: Bonus Equity Share Capital | B50: 482.74 | C50: 482.74 | D50: 482.74 | E50: 482.74 | F50: 482.74
A51: NON-CURRENT INVESTMENTS
A52: Non-Current Investments Quoted Market Value | B52: 0 | C52: 0 | D52: 0 | E52: 0 | F52: 0
A53: Non-Current Investments Unquoted Book Value | B53: 91 | C53: 94 | D53: 110 | E53: 103 | F53: 89
A54: CURRENT INVESTMENTS
A55: Current Investments Quoted Market Value | B55: 4309 | C55: 3491 | D55: 3601 | E55: 3783 | F55: 5749
A56: Current Investments Unquoted Book Value | B56: 3255 | C56: 3646 | D56: 1784 | E56: 2456 | F56: 1024
A58: P&L
A59: Particulars | B59: FY2025 | C59: FY2024 | D59: FY2023 | E59: FY2022 | F59: FY2021
A60: INCOME
A61: Revenue From Operations [Gross] | B61: 117055 | C61: 109913 | D61: 101456 | E61: 85651 | F61: 75379
A62: Less: Excise/Sevice Tax/Other Levies | B62: 0 | C62: 0 | D62: 0 | E62: 0 | F62: 0
A63: Revenue From Operations [Net] | B63: 117055 | C63: 109913 | D63: 101456 | E63: 85651 | F63: 75379
A64: Total Operating Revenues | B64: 117055 | C64: 109913 | D64: 101456 | E64: 85651 | F64: 75379
A65: Other Income | B65: 2485 | C65: 1495 | D65: 1358 | E65: 1067 | F65: 927
A66: Total Revenue | B66: 119540 | C66: 111408 | D66: 102814 | E66: 86718 | F66: 76306
A67: EXPENSES
A68: Cost Of Materials Consumed | B68: 0 | C68: 0 | D68: 0 | E68: 0 | F68: 0
A69: Purchase Of Stock-In Trade | B69: 1976 | C69: 1754 | D69: 2072 | E69: 1473 | F69: 1698
A70: Operating And Direct Expenses | B70: 15162 | C70: 14578 | D70: 14950 | E70: 12515 | F70: 10158
A71: Changes In Inventories Of FGWIP And Stock In Trade | B71: 52 | C71: 43 | D71: -67 | E71: -67 | F71: -3
A72: Employee Benefit Expenses | B72: 66755 | C72: 62480 | D72: 55280 | E72: 46130 | F72: 38853
A73: Finance Costs | B73: 644 | C73: 553 | D73: 353 | E73: 319 | F73: 511
A74: Depreciation And Amortisation Expenses | B74: 4084 | C74: 4173 | D74: 4145 | E74: 4326 | F74: 4611
A75: Other Expenses | B75: 7606 | C75: 6860 | D75: 6593 | E75: 5070 | F75: 4625
A76: Total Expenses | B76: 96279 | C76: 90441 | D76: 83326 | E76: 69766 | F76: 60453
A77: Profit/Loss Before Exceptional, ExtraOrdinary Items And Tax | B77: 23261 | C77: 20967 | D77: 19488 | E77: 16952 | F77: 15853
A78: Exceptional Items | B78: 0 | C78: 0 | D78: 0 | E78: 0 | F78: 0
A79: Profit/Loss Before Tax | B79: 23261 | C79: 20967 | D79: 19488 | E79: 16952 | F79: 15853
A80: Tax Expenses-Continued Operations
A81: Current Tax | B81: 5161 | C81: 4626 | D81: 4665 | E81: 3442 | F81: 3719
A82: Less: MAT Credit Entitlement | B82: 0 | C82: 0 | D82: 0 | E82: 0 | F82: 0
A83: Deferred Tax | B83: 701 | C83: 631 | D83: -22 | E83: -14 | F83: 965
A84: Other Direct Taxes | B84: 0 | C84: 0 | D84: 0 | E84: 0 | F84: 0
A85: Total Tax Expenses | B85: 5862 | C85: 5257 | D85: 4643 | E85: 3428 | F85: 4684
A86: Profit/Loss After Tax And Before ExtraOrdinary Items | B86: 17399 | C86: 15710 | D86: 14845 | E86: 13524 | F86: 11169
A87: Profit/Loss From Continuing Operations | B87: 17399 | C87: 15710 | D87: 14845 | E87: 13524 | F87: 11169
A88: Profit/Loss For The Period | B88: 17399 | C88: 15710 | D88: 14845 | E88: 13524 | F88: 11169
A89: Minority Interest | B89: -9 | C89: -8 | D89: 6 | E89: -24 | F89: -24
A90: Consolidated Profit/Loss After MI And Associates | B90: 17390 | C90: 15702 | D90: 14851 | E90: 13499 | F90: 11145
A91: OTHER ADDITIONAL INFORMATION
A92: EARNINGS PER SHARE
A93: Basic EPS (Rs.) | B93: 64 | C93: 58 | D93: 55 | E93: 50 | F93: 41
A94: Diluted EPS (Rs.) | B94: 64 | C94: 58 | D94: 55 | E94: 50 | F94: 41
A95: DIVIDEND AND DIVIDEND PERCENTAGE
A96: Equity Share Dividend | B96: 16254 | C96: 14080 | D96: 12995 | E96: 11391 | F96: 3257
A97: Tax On Dividend | B97: 0 | C97: 0 | D97: 0 | E97: 0 | F97: 0
A99: CASH FLOW
A100: Particulars | B100: FY2025 | C100: FY2024 | D100: FY2023 | E100: FY2022 | F100: FY2021
A101: Net Profit/Loss Before Extraordinary Items And Tax | B101: 23261 | C101: 20967 | D101: 19488 | E101: 16951 | F101: 15853
A102: Net CashFlow From Operating Activities | B102: 22261 | C102: 22448 | D102: 18009 | E102: 16900 | F102: 19618
A103: Net Cash Used In Investing Activities | B103: -4914 | C103: -6723 | D103: -3931 | E103: 1477 | F103: -5742
...

Sheet Wipro_Data
A1: Wipro Ltd. - Consolidated Financial Data (Rs Cr)
A3: BALANCE SHEET
A4: Particulars | B4: FY2025 | C4: FY2024 | D4: FY2023 | E4: FY2022 | F4: FY2021
A5: EQUITIES AND LIABILITIES
A6: SHAREHOLDER'S FUNDS
A7: Equity Share Capital | B7: 2094.4 | C7: 1045 | D7: 1097.6 | E7: 1096.4 | F7: 1095.8
A8: Total Share Capital | B8: 2094.4 | C8: 1045 | D8: 1097.6 | E8: 1096.4 | F8: 1095.8
A9: Reserves and Surplus | B9: 80269.7 | C9: 73488 | D9: 76570.3 | E9: 64306.6 | F9: 53805.2
A10: Total Reserves and Surplus | B10: 80269.7 | C10: 73488 | D10: 76570.3 | E10: 64306.6 | F10: 53805.2
A11: Total Shareholders Funds | B11: 82364.1 | C11: 74533 | D11: 77667.9 | E11: 65403 | F11: 54901
A12: Minority Interest | B12: 213.8 | C12: 134 | D12: 58.9 | E12: 51.5 | F12: 149.8
A13: NON-CURRENT LIABILITIES
A14: Long Term Borrowings | B14: 6395.4 | C14: 6230 | D14: 6127.2 | E14: 5646.3 | F14: 745.8
A15: Deferred Tax Liabilities [Net] | B15: 1644.3 | C15: 1746.7 | D15: 1515.3 | E15: 1214.1 | F15: 460.6
A16: Other Long Term Liabilities | B16: 8476.7 | C16: 6479.2 | D16: 4694.4 | E16: 4085.5 | F16: 3165.3
A17: Long Term Provisions | B17: 465.6 | C17: 421.9 | D17: 294.7 | E17: 272.1 | F17: 305.7
A18: Total Non-Current Liabilities | B18: 16982 | C18: 14877.8 | D18: 12631.6 | E18: 11218 | F18: 4677.4
A19: CURRENT LIABILITIES
A20: Short Term Borrowings | B20: 9786.3 | C20: 7916.6 | D20: 8882.1 | E20: 9523.3 | F20: 6036.3
A21: Trade Payables | B21: 5866.7 | C21: 5765.5 | D21: 5972.3 | E21: 6252.2 | F21: 5417.4 | G21: 5840
A22: Other Current Liabilities | B22: 11208.5 | C22: 9760.9 | D22: 10077.5 | E22: 13249.3 | F22: 10002.5
A23: Short Term Provisions | B23: 1763.8 | C23: 1802.8 | D23: 1843.4 | E23: 1808.1 | F23: 1547.8
A24: Total Current Liabilities | B24: 28625.3 | C24: 25245.8 | D24: 26775.3 | E24: 30832.9 | F24: 23004
A25: Total Capital And Liabilities | B25: 128185.2 | C25: 114790.6 | D25: 117133.7 | E25: 107505.4 | F25: 82732.2
A26: ASSETS
A27: NON-CURRENT ASSETS
A28: Tangible Assets | B28: 10407.1 | C28: 9208.3 | D28: 10103.8 | E28: 9348 | F28: 8217.1
A29: Intangible Assets | B29: 2745 | C29: 3274.8 | D29: 4304.5 | E29: 4355.5 | F29: 1308.5
A30: Capital Work-In-Progress | B30: 196.4 | C30: 723.4 | D30: 617.1 | E30: 1601.5 | F30: 1853.2
A31: Fixed Assets | B31: 13348.5 | C31: 13206.5 | D31: 15025.4 | E31: 15305 | F31: 11378.8
A32: Non-Current Investments | B32: 2778.5 | C32: 2267.3 | D32: 2150 | E32: 1988.3 | F32: 1204
A33: Deferred Tax Assets [Net] | B33: 256.1 | C33: 181.7 | D33: 210 | E33: 229.8 | F33: 166.4
A34: Long Term Loans And Advances | B34: 0 | C34: 0 | D34: 0 | E34: 0 | F34: 0
A35: Other Non-Current Assets | B35: 1990 | C35: 2924 | D35: 3290.2 | E35: 3621 | F35: 4149.7
A36: Total Non-Current Assets | B36: 50407.7 | C36: 49724.4 | D36: 51024.1 | E36: 45430.2 | F36: 30413.6
A37: CURRENT ASSETS
A38: Current Investments | B38: 41147.4 | C38: 31117.1 | D38: 30923.2 | E38: 24165.5 | F38: 17570.7
A39: Inventories | B39: 69.4 | C39: 90.7 | D39: 118.8 | E39: 133.4 | F39: 106.4 | G39: 186.5
A40: Trade Receivables | B40: 11774.5 | C40: 17382.2 | D40: 18686.5 | E40: 11521.9 | F40: 9429.8 | G40: 10447.4
A41: Cash And Cash Equivalents | B41: 12197.4 | C41: 9695.3 | D41: 9188 | E41: 10383.6 | F41: 16979.3
A42: Short Term Loans And Advances | B42: 0 | C42: 0 | D42: 0 | E42: 0 | F42: 0
A43: OtherCurrentAssets | B43: 12588.8 | C43: 6780.9 | D43: 7193.1 | E43: 15870.8 | F43: 8232.4
A44: Total Current Assets | B44: 77777.5 | C44: 65066.2 | D44: 66109.6 | E44: 62075.2 | F44: 52318.6
A45: Total Assets | B45: 128185.2 | C45: 114790.6 | D45: 117133.7 | E45: 107505.4 | F45: 82732.2
A46: OTHER ADDITIONAL INFORMATION
A47: CONTINGENT LIABILITIES, COMMITMENTS
A48: Contingent Liabilities | B48: 14055.2 | C48: 13453.7 | D48: 13045.6 | E48: 13307.2 | F48: 11606.3
A49: BONUS DETAILS
A50: Bonus Equity Share Capital | B50: 2088.6 | C50: 1041.9 | D50: 1094.34 | E50: 1094.34 | F50: 1094.34
A51: NON-CURRENT INVESTMENTS
A52: Non-Current Investments Quoted Market Value | B52: 5.7 | C52: 10.8 | D52: 3.3 | E52: 4.1 | F52: 2.6
A53: Non-Current Investments Unquoted Book Value | B53: 2640.1 | C53: 2152.1 | D53: 2068.7 | E53: 1906.8 | F53: 1055
A54: CURRENT INVESTMENTS
A55: Current Investments Quoted Market Value | B55: 25403.6 | C55: 20147.7 | D55: 22836.7 | E55: 19090.2 | F55: 13138.2
A56: Current Investments Unquoted Book Value | B56: 15743.8 | C56: 10969.4 | D56: 8086.5 | E56: 5075.3 | F56: 4432.5
A58: P & L
A59: Particulars | B59: FY2025 | C59: FY2024 | D59: FY2023 | E59: FY2022 | F59: FY2021
A60: INCOME
A61: Revenue From Operations [Gross] | B61: 89088.4 | C61: 89760.3 | D61: 90487.6 | E61: 79093.4 | F61: 61943
A62: Less: Excise/Sevice Tax/Other Levies | B62: 0 | C62: 0 | D62: 0 | E62: 0 | F62: 0
A63: Revenue From Operations [Net] | B63: 89088.4 | C63: 89760.3 | D63: 90487.6 | E63: 79093.4 | F63: 61943
A64: Total Operating Revenues | B64: 89088.4 | C64: 89760.3 | D64: 90487.6 | E64: 79312 | F64: 61934.9
A65: Other Income | B65: 3884 | C65: 2630.8 | D65: 2265.7 | E65: 2061.2 | F65: 2390.7
A66: Total Revenue | B66: 92972.4 | C66: 92391.1 | D66: 92753.3 | E66: 81373.2 | F66: 64325.6
A67: EXPENSES
A68: Cost Of Materials Consumed | B68: 0 | C68: 0 | D68: 0 | E68: 0 | F68: 0
A69: Purchase Of Stock-In Trade | B69: 296.7 | C69: 383.2 | D69: 649.4 | E69: 673.5 | F69: 695.7
A70: Operating And Direct Expenses | B70: 12332.8 | C70: 14084.2 | D70: 15336.7 | E70: 15449.9 | F70: 12075.2
A71: Changes In Inventories Of FGWIP And Stock In Trade | B71: 19.5 | C71: 27.8 | D71: 15 | E71: -36.9 | F71: 31.5
A72: Employee Benefit Expenses | B72: 53347.7 | C72: 54930.1 | D72: 53764.4 | E72: 45007.5 | F72: 33237.1
A73: Finance Costs | B73: 1477 | C73: 1255.2 | D73: 1007.7 | E73: 532.5 | F73: 508.8
A74: Depreciation And Amortisation Expenses | B74: 2957.9 | C74: 3407.1 | D74: 3340.2 | E74: 3077.8 | F74: 2763.4
A75: Other Expenses | B75: 5070.5 | C75: 3559.2 | D75: 3868.5 | E75: 1533.8 | F75: 1124
A76: Total Expenses | B76: 75502.1 | C76: 77646.8 | D76: 77981.9 | E76: 66238.1 | F76: 50435.7
A77: Profit/Loss Before Exceptional, ExtraOrdinary Items And Tax | B77: 17470.3 | C77: 14744.3 | D77: 14771.4 | E77: 15135.1 | F77: 13889.9
A78: Exceptional Items | B78: 0 | C78: 0 | D78: 0 | E78: 0 | F78: 0
A79: Profit/Loss Before Tax | B79: 17470.3 | C79: 14744.3 | D79: 14771.4 | E79: 15135.1 | F79: 13889.9
A80: Tax Expenses-Continued Operations
A81: Current Tax | B81: 4540.5 | C81: 3497.3 | D81: 3219.8 | E81: 3241.5 | F81: 2606.5
A82: Less: MAT Credit Entitlement | B82: 0 | C82: 0 | D82: 0 | E82: 0 | F82: 0
A83: Deferred Tax | B83: -262.8 | C83: 111.6 | D83: 179.4 | E83: -344.1 | F83: 428.4
A84: Other Direct Taxes | B84: 0 | C84: 0 | D84: 0 | E84: 0 | F84: 0
A85: Total Tax Expenses | B85: 4277.7 | C85: 3608.9 | D85: 3399.2 | E85: 2897.4 | F85: 3034.9
A86: Profit/Loss After Tax And Before ExtraOrdinary Items | B86: 13192.6 | C86: 11135.4 | D86: 11372.2 | E86: 12237.7 | F86: 10855
A87: Profit/Loss From Continuing Operations | B87: 13192.6 | C87: 11135.4 | D87: 11372.2 | E87: 12237.7 | F87: 10855
A88: Profit/Loss For The Period | B88: 13192.6 | C88: 11135.4 | D88: 11372.2 | E88: 12237.7 | F88: 10855
A89: Minority Interest | B89: -82.6 | C89: -66.9 | D89: -16.5 | E89: -13.8 | F89: -71.6
A90: Consolidated Profit/Loss After MI And Associates | B90: 13135.4 | C90: 11045.2 | D90: 11350 | E90: 12229.6 | F90: 10796.4
A91: OTHER ADDITIONAL INFORMATION
A92: EARNINGS PER SHARE
A93: Basic EPS (Rs.) | B93: 13 | C93: 21 | D93: 21 | E93: 22 | F93: 19
A94: Diluted EPS (Rs.) | B94: 13 | C94: 21 | D94: 21 | E94: 22 | F94: 19
A95: DIVIDEND AND DIVIDEND PERCENTAGE
A96: Equity Share Dividend | B96: 6275 | C96: 521.8 | D96: 547.7 | E96: 3280.4 | F96: 545.9
A97: Tax On Dividend | B97: 0 | C97: 0 | D97: 0 | E97: 0 | F97: 0
A99: CASH FLOW
A100: Particulars | B100: FY2025 | C100: FY2024 | D100: FY2023 | E100: FY2022 | F100: FY2021
A101: Net Profit/Loss Before Extraordinary Items And Tax | B101: 13218 | C101: 11112.1 | D101: 11366.5 | E101: 12243.4 | F101: 10868
A102: Net CashFlow From Operating Activities | B102: 16942.6 | C102: 17621.6 | D102: 13060.1 | E102: 11079.7 | F102: 14755
A103: Net Cash Used In Investing Activities | B103: -8073 | C103: 1168 | D103: -8406.5 | E103: -22449.5 | F103: 773.9
...

Sheet Ratios
A1: Financial Ratios - HCL Technologies vs Wipro (FY2021-FY2025)
B3: HCL Technologies | H3: Wipro
A4: Ratio | B4: HCL FY2025 | C4: HCL FY2024 | D4: HCL FY2023 | E4: HCL FY2022 | F4: HCL FY2021 | H4: Wipro FY2025 | I4: Wipro FY2024 | J4: Wipro FY2023 | K4: Wipro FY2022 | L4: Wipro FY2021
A5: LIQUIDITY RATIOS
A6: Current Ratio | B6: =HCL_Data!B44/HCL_Data!B24 | C6: =HCL_Data!C44/HCL_Data!C24 | D6: =HCL_Data!D44/HCL_Data!D24 | E6: =HCL_Data!E44/HCL_Data!E24 | F6: =HCL_Data!F44/HCL_Data!F24 | H6: =Wipro_Data!B44/Wipro_Data!B24 | I6: =Wipro_Data!C44/Wipro_Data!C24 | J6: =Wipro_Data!D44/Wipro_Data!D24 | K6: =Wipro_Data!E44/Wipro_Data!E24 | L6: =Wipro_Data!F44/Wipro_Data!F24
A7: Quick Ratio | B7: =(HCL_Data!B44-HCL_Data!B39)/HCL_Data!B24 | C7: =(HCL_Data!C44-HCL_Data!C39)/HCL_Data!C24 | D7: =(HCL_Data!D44-HCL_Data!D39)/HCL_Data!D24 | E7: =(HCL_Data!E44-HCL_Data!E39)/HCL_Data!E24 | F7: =(HCL_Data!F44-HCL_Data!F39)/HCL_Data!F24 | H7: =(Wipro_Data!B44-Wipro_Data!B39)/Wipro_Data!B24 | I7: =(Wipro_Data!C44-Wipro_Data!C39)/Wipro_Data!C24 | J7: =(Wipro_Data!D44-Wipro_Data!D39)/Wipro_Data!D24 | K7: =(Wipro_Data!E44-Wipro_Data!E39)/Wipro_Data!E24 | L7: =(Wipro_Data!F44-Wipro_Data!F39)/Wipro_Data!F24
A8: Absolute Liquid Ratio | B8: =(HCL_Data!B41+HCL_Data!B38)/HCL_Data!B24 | C8: =(HCL_Data!C41+HCL_Data!C38)/HCL_Data!C24 | D8: =(HCL_Data!D41+HCL_Data!D38)/HCL_Data!D24 | E8: =(HCL_Data!E41+HCL_Data!E38)/HCL_Data!E24 | F8: =(HCL_Data!F41+HCL_Data!F38)/HCL_Data!F24 | H8: =(Wipro_Data!B41+Wipro_Data!B38)/Wipro_Data!B24 | I8: =(Wipro_Data!C41+Wipro_Data!C38)/Wipro_Data!C24 | J8: =(Wipro_Data!D41+Wipro_Data!D38)/Wipro_Data!D24 | K8: =(Wipro_Data!E41+Wipro_Data!E38)/Wipro_Data!E24 | L8: =(Wipro_Data!F41+Wipro_Data!F38)/Wipro_Data!F24
A9: PROFITABILITY RATIOS
A10: Gross Profit Ratio (%) | B10: =(HCL_Data!B63-(HCL_Data!B69+HCL_Data!B70+HCL_Data!B71))/HCL_Data!B63*100 | C10: =(HCL_Data!C63-(HCL_Data!C69+HCL_Data!C70+HCL_Data!C71))/HCL_Data!C63*100 | D10: =(HCL_Data!D63-(HCL_Data!D69+HCL_Data!D70+HCL_Data!D71))/HCL_Data!D63*100 | E10: =(HCL_Data!E63-(HCL_Data!E69+HCL_Data!E70+HCL_Data!E71))/HCL_Data!E63*100 | F10: =(HCL_Data!F63-(HCL_Data!F69+HCL_Data!F70+HCL_Data!F71))/HCL_Data!F63*100 | H10: =(Wipro_Data!B63-(Wipro_Data!B69+Wipro_Data!B70+Wipro_Data!B71))/Wipro_Data!B63*100 | I10: =(Wipro_Data!C63-(Wipro_Data!C69+Wipro_Data!C70+Wipro_Data!C71))/Wipro_Data!C63*100 | J10: =(Wipro_Data!D63-(Wipro_Data!D69+Wipro_Data!D70+Wipro_Data!D71))/Wipro_Data!D63*100 | K10: =(Wipro_Data!E63-(Wipro_Data!E69+Wipro_Data!E70+Wipro_Data!E71))/Wipro_Data!E63*100 | L10: =(Wipro_Data!F63-(Wipro_Data!F69+Wipro_Data!F70+Wipro_Data!F71))/Wipro_Data!F63*100
A11: Operating Profit Ratio (%) | B11: =(HCL_Data!B79+HCL_Data!B73)/HCL_Data!B63*100 | C11: =(HCL_Data!C79+HCL_Data!C73)/HCL_Data!C63*100 | D11: =(HCL_Data!D79+HCL_Data!D73)/HCL_Data!D63*100 | E11: =(HCL_Data!E79+HCL_Data!E73)/HCL_Data!E63*100 | F11: =(HCL_Data!F79+HCL_Data!F73)/HCL_Data!F63*100 | H11: =(Wipro_Data!B79+Wipro_Data!B73)/Wipro_Data!B63*100 | I11: =(Wipro_Data!C79+Wipro_Data!C73)/Wipro_Data!C63*100 | J11: =(Wipro_Data!D79+Wipro_Data!D73)/Wipro_Data!D63*100 | K11: =(Wipro_Data!E79+Wipro_Data!E73)/Wipro_Data!E63*100 | L11: =(Wipro_Data!F79+Wipro_Data!F73)/Wipro_Data!F63*100
A12: Net Profit Ratio (%) | B12: =HCL_Data!B88/HCL_Data!B63*100 | C12: =HCL_Data!C88/HCL_Data!C63*100 | D12: =HCL_Data!D88/HCL_Data!D63*100 | E12: =HCL_Data!E88/HCL_Data!E63*100 | F12: =HCL_Data!F88/HCL_Data!F63*100 | H12: =Wipro_Data!B88/Wipro_Data!B63*100 | I12: =Wipro_Data!C88/Wipro_Data!C63*100 | J12: =Wipro_Data!D88/Wipro_Data!D63*100 | K12: =Wipro_Data!E88/Wipro_Data!E63*100 | L12: =Wipro_Data!F88/Wipro_Data!F63*100
A13: Return on Equity (%) | B13: =HCL_Data!B88/((HCL_Data!B11+HCL_Data!C11)/2)*100 | C13: =HCL_Data!C88/((HCL_Data!C11+HCL_Data!D11)/2)*100 | D13: =HCL_Data!D88/((HCL_Data!D11+HCL_Data!E11)/2)*100 | E13: =HCL_Data!E88/((HCL_Data!E11+HCL_Data!F11)/2)*100 | F13: =HCL_Data!F88/((HCL_Data!F11+HCL_Data!F11)/2)*100 | H13: =Wipro_Data!B88/((Wipro_Data!B11+Wipro_Data!C11)/2)*100 | I13: =Wipro_Data!C88/((Wipro_Data!C11+Wipro_Data!D11)/2)*100 | J13: =Wipro_Data!D88/((Wipro_Data!D11+Wipro_Data!E11)/2)*100 | K13: =Wipro_Data!E88/((Wipro_Data!E11+Wipro_Data!F11)/2)*100 | L13: =Wipro_Data!F88/((Wipro_Data!F11+Wipro_Data!F11)/2)*100
A14: Return on Capital Employed (%) | B14: =(HCL_Data!B79+HCL_Data!B73)/(HCL_Data!B45-HCL_Data!B24)*100 | C14: =(HCL_Data!C79+HCL_Data!C73)/(HCL_Data!C45-HCL_Data!C24)*100 | D14: =(HCL_Data!D79+HCL_Data!D73)/(HCL_Data!D45-HCL_Data!D24)*100 | E14: =(HCL_Data!E79+HCL_Data!E73)/(HCL_Data!E45-HCL_Data!E24)*100 | F14: =(HCL_Data!F79+HCL_Data!F73)/(HCL_Data!F45-HCL_Data!F24)*100 | H14: =(Wipro_Data!B79+Wipro_Data!B73)/(Wipro_Data!B45-Wipro_Data!B24)*100 | I14: =(Wipro_Data!C79+Wipro_Data!C73)/(Wipro_Data!C45-Wipro_Data!C24)*100 | J14: =(Wipro_Data!D79+Wipro_Data!D73)/(Wipro_Data!D45-Wipro_Data!D24)*100 | K14: =(Wipro_Data!E79+Wipro_Data!E73)/(Wipro_Data!E45-Wipro_Data!E24)*100 | L14: =(Wipro_Data!F79+Wipro_Data!F73)/(Wipro_Data!F45-Wipro_Data!F24)*100
A15: Earnings per Share (Rs) | B15: =HCL_Data!B90/(HCL_Data!B7/2) | C15: =HCL_Data!C90/(HCL_Data!C7/2) | D15: =HCL_Data!D90/(HCL_Data!D7/2) | E15: =HCL_Data!E90/(HCL_Data!E7/2) | F15: =HCL_Data!F90/(HCL_Data!F7/2) | H15: =Wipro_Data!B90/(Wipro_Data!B7/2) | I15: =Wipro_Data!C90/(Wipro_Data!C7/2) | J15: =Wipro_Data!D90/(Wipro_Data!D7/2) | K15: =Wipro_Data!E90/(Wipro_Data!E7/2) | L15: =Wipro_Data!F90/(Wipro_Data!F7/2)
A16: SOLVENCY RATIOS
A17: Debt-Equity Ratio | B17: =(HCL_Data!B14+HCL_Data!B20)/HCL_Data!B11 | C17: =(HCL_Data!C14+HCL_Data!C20)/HCL_Data!C11 | D17: =(HCL_Data!D14+HCL_Data!D20)/HCL_Data!D11 | E17: =(HCL_Data!E14+HCL_Data!E20)/HCL_Data!E11 | F17: =(HCL_Data!F14+HCL_Data!F20)/HCL_Data!F11 | H17: =(Wipro_Data!B14+Wipro_Data!B20)/Wipro_Data!B11 | I17: =(Wipro_Data!C14+Wipro_Data!C20)/Wipro_Data!C11 | J17: =(Wipro_Data!D14+Wipro_Data!D20)/Wipro_Data!D11 | K17: =(Wipro_Data!E14+Wipro_Data!E20)/Wipro_Data!E11 | L17: =(Wipro_Data!F14+Wipro_Data!F20)/Wipro_Data!F11
A18: Interest Coverage Ratio | B18: =(HCL_Data!B79+HCL_Data!B73)/HCL_Data!B73 | C18: =(HCL_Data!C79+HCL_Data!C73)/HCL_Data!C73 | D18: =(HCL_Data!D79+HCL_Data!D73)/HCL_Data!D73 | E18: =(HCL_Data!E79+HCL_Data!E73)/HCL_Data!E73 | F18: =(HCL_Data!F79+HCL_Data!F73)/HCL_Data!F73 | H18: =(Wipro_Data!B79+Wipro_Data!B73)/Wipro_Data!B73 | I18: =(Wipro_Data!C79+Wipro_Data!C73)/Wipro_Data!C73 | J18: =(Wipro_Data!D79+Wipro_Data!D73)/Wipro_Data!D73 | K18: =(Wipro_Data!E79+Wipro_Data!E73)/Wipro_Data!E73 | L18: =(Wipro_Data!F79+Wipro_Data!F73)/Wipro_Data!F73
A19: TURNOVER RATIOS
A20: Debtors Turnover Ratio | B20: =HCL_Data!B63/((HCL_Data!B40+HCL_Data!C40)/2) | C20: =HCL_Data!C63/((HCL_Data!C40+HCL_Data!D40)/2) | D20: =HCL_Data!D63/((HCL_Data!D40+HCL_Data!E40)/2) | E20: =HCL_Data!E63/((HCL_Data!E40+HCL_Data!F40)/2) | F20: =HCL_Data!F63/((HCL_Data!F40+HCL_Data!F40)/2) | H20: =Wipro_Data!B63/((Wipro_Data!B40+Wipro_Data!C40)/2) | I20: =Wipro_Data!C63/((Wipro_Data!C40+Wipro_Data!D40)/2) | J20: =Wipro_Data!D63/((Wipro_Data!D40+Wipro_Data!E40)/2) | K20: =Wipro_Data!E63/((Wipro_Data!E40+Wipro_Data!F40)/2) | L20: =Wipro_Data!F63/((Wipro_Data!F40+Wipro_Data!F40)/2)
A21: Avg Collection Period (days) | B21: =365/(HCL_Data!B63/((HCL_Data!B40+HCL_Data!C40)/2)) | C21: =365/(HCL_Data!C63/((HCL_Data!C40+HCL_Data!D40)/2)) | D21: =365/(HCL_Data!D63/((HCL_Data!D40+HCL_Data!E40)/2)) | E21: =365/(HCL_Data!E63/((HCL_Data!E40+HCL_Data!F40)/2)) | F21: =365/(HCL_Data!F63/((HCL_Data!F40+HCL_Data!F40)/2)) | H21: =365/(Wipro_Data!B63/((Wipro_Data!B40+Wipro_Data!C40)/2)) | I21: =365/(Wipro_Data!C63/((Wipro_Data!C40+Wipro_Data!D40)/2)) | J21: =365/(Wipro_Data!D63/((Wipro_Data!D40+Wipro_Data!E40)/2)) | K21: =365/(Wipro_Data!E63/((Wipro_Data!E40+Wipro_Data!F40)/2)) | L21: =365/(Wipro_Data!F63/((Wipro_Data!F40+Wipro_Data!F40)/2))
A22: Creditors Turnover Ratio | B22: =(HCL_Data!B69+HCL_Data!B70+HCL_Data!B75)/((HCL_Data!B21+HCL_Data!C21)/2) | C22: =(HCL_Data!C69+HCL_Data!C70+HCL_Data!C75)/((HCL_Data!C21+HCL_Data!D21)/2) | D22: =(HCL_Data!D69+HCL_Data!D70+HCL_Data!D75)/((HCL_Data!D21+HCL_Data!E21)/2) | E22: =(HCL_Data!E69+HCL_Data!E70+HCL_Data!E75)/((HCL_Data!E21+HCL_Data!F21)/2) | F22: =(HCL_Data!F69+HCL_Data!F70+HCL_Data!F75)/((HCL_Data!F21+HCL_Data!F21)/2) | H22: =(Wipro_Data!B69+Wipro_Data!B70+Wipro_Data!B75)/((Wipro_Data!B21+Wipro_Data!C21)/2) | I22: =(Wipro_Data!C69+Wipro_Data!C70+Wipro_Data!C75)/((Wipro_Data!C21+Wipro_Data!D21)/2) | J22: =(Wipro_Data!D69+Wipro_Data!D70+Wipro_Data!D75)/((Wipro_Data!D21+Wipro_Data!E21)/2) | K22: =(Wipro_Data!E69+Wipro_Data!E70+Wipro_Data!E75)/((Wipro_Data!E21+Wipro_Data!F21)/2) | L22: =(Wipro_Data!F69+Wipro_Data!F70+Wipro_Data!F75)/((Wipro_Data!F21+Wipro_Data!F21)/2)
A23: Avg Payment Period (days) | B23: =365/((HCL_Data!B69+HCL_Data!B70+HCL_Data!B75)/((HCL_Data!B21+HCL_Data!C21)/2)) | C23: =365/((HCL_Data!C69+HCL_Data!C70+HCL_Data!C75)/((HCL_Data!C21+HCL_Data!D21)/2)) | D23: =365/((HCL_Data!D69+HCL_Data!D70+HCL_Data!D75)/((HCL_Data!D21+HCL_Data!E21)/2)) | E23: =365/((HCL_Data!E69+HCL_Data!E70+HCL_Data!E75)/((HCL_Data!E21+HCL_Data!F21)/2)) | F23: =365/((HCL_Data!F69+HCL_Data!F70+HCL_Data!F75)/((HCL_Data!F21+HCL_Data!F21)/2)) | H23: =365/((Wipro_Data!B69+Wipro_Data!B70+Wipro_Data!B75)/((Wipro_Data!B21+Wipro_Data!C21)/2)) | I23: =365/((Wipro_Data!C69+Wipro_Data!C70+Wipro_Data!C75)/((Wipro_Data!C21+Wipro_Data!D21)/2)) | J23: =365/((Wipro_Data!D69+Wipro_Data!D70+Wipro_Data!D75)/((Wipro_Data!D21+Wipro_Data!E21)/2)) | K23: =365/((Wipro_Data!E69+Wipro_Data!E70+Wipro_Data!E75)/((Wipro_Data!E21+Wipro_Data!F21)/2)) | L23: =365/((Wipro_Data!F69+Wipro_Data!F70+Wipro_Data!F75)/((Wipro_Data!F21+Wipro_Data!F21)/2))
A24: Inventory Turnover Ratio | B24: =(HCL_Data!B69+HCL_Data!B70+HCL_Data!B71)/((HCL_Data!B39+HCL_Data!C39)/2) | C24: =(HCL_Data!C69+HCL_Data!C70+HCL_Data!C71)/((HCL_Data!C39+HCL_Data!D39)/2) | D24: =(HCL_Data!D69+HCL_Data!D70+HCL_Data!D71)/((HCL_Data!D39+HCL_Data!E39)/2) | E24: =(HCL_Data!E69+HCL_Data!E70+HCL_Data!E71)/((HCL_Data!E39+HCL_Data!F39)/2) | F24: =(HCL_Data!F69+HCL_Data!F70+HCL_Data!F71)/((HCL_Data!F39+HCL_Data!F39)/2) | H24: =(Wipro_Data!B69+Wipro_Data!B70+Wipro_Data!B71)/((Wipro_Data!B39+Wipro_Data!C39)/2) | I24: =(Wipro_Data!C69+Wipro_Data!C70+Wipro_Data!C71)/((Wipro_Data!C39+Wipro_Data!D39)/2) | J24: =(Wipro_Data!D69+Wipro_Data!D70+Wipro_Data!D71)/((Wipro_Data!D39+Wipro_Data!E39)/2) | K24: =(Wipro_Data!E69+Wipro_Data!E70+Wipro_Data!E71)/((Wipro_Data!E39+Wipro_Data!F39)/2) | L24: =(Wipro_Data!F69+Wipro_Data!F70+Wipro_Data!F71)/((Wipro_Data!F39+Wipro_Data!F39)/2)
A25: Inventory Holding Days | B25: =365/((HCL_Data!B69+HCL_Data!B70+HCL_Data!B71)/((HCL_Data!B39+HCL_Data!C39)/2)) | C25: =365/((HCL_Data!C69+HCL_Data!C70+HCL_Data!C71)/((HCL_Data!C39+HCL_Data!D39)/2)) | D25: =365/((HCL_Data!D69+HCL_Data!D70+HCL_Data!D71)/((HCL_Data!D39+HCL_Data!E39)/2)) | E25: =365/((HCL_Data!E69+HCL_Data!E70+HCL_Data!E71)/((HCL_Data!E39+HCL_Data!F39)/2)) | F25: =365/((HCL_Data!F69+HCL_Data!F70+HCL_Data!F71)/((HCL_Data!F39+HCL_Data!F39)/2)) | H25: =365/((Wipro_Data!B69+Wipro_Data!B70+Wipro_Data!B71)/((Wipro_Data!B39+Wipro_Data!C39)/2)) | I25: =365/((Wipro_Data!C69+Wipro_Data!C70+Wipro_Data!C71)/((Wipro_Data!C39+Wipro_Data!D39)/2)) | J25: =365/((Wipro_Data!D69+Wipro_Data!D70+Wipro_Data!D71)/((Wipro_Data!D39+Wipro_Data!E39)/2)) | K25: =365/((Wipro_Data!E69+Wipro_Data!E70+Wipro_Data!E71)/((Wipro_Data!E39+Wipro_Data!F39)/2)) | L25: =365/((Wipro_Data!F69+Wipro_Data!F70+Wipro_Data!F71)/((Wipro_Data!F39+Wipro_Data!F39)/2))
A26: Fixed Asset Turnover | B26: =HCL_Data!B63/((HCL_Data!B31+HCL_Data!C31)/2) | C26: =HCL_Data!C63/((HCL_Data!C31+HCL_Data!D31)/2) | D26: =HCL_Data!D63/((HCL_Data!D31+HCL_Data!E31)/2) | E26: =HCL_Data!E63/((HCL_Data!E31+HCL_Data!F31)/2) | F26: =HCL_Data!F63/((HCL_Data!F31+HCL_Data!F31)/2) | H26: =Wipro_Data!B63/((Wipro_Data!B31+Wipro_Data!C31)/2) | I26: =Wipro_Data!C63/((Wipro_Data!C31+Wipro_Data!D31)/2) | J26: =Wipro_Data!D63/((Wipro_Data!D31+Wipro_Data!E31)/2) | K26: =Wipro_Data!E63/((Wipro_Data!E31+Wipro_Data!F31)/2) | L26: =Wipro_Data!F63/((Wipro_Data!F31+Wipro_Data!F31)/2)
A27: VALUATION RATIOS
A28: Price/BV (X) from Money Control | B28: 6.2 | C28: 6.14 | D28: 4.51 | E28: 5.1 | F28: 4.46 | H28: 3.33 | I28: 3.37 | J28: 2.58 | K28: 4.96 | L28: 4.13
A29: Book Value/Share (Rs.) from Money Control | B29: 256.56 | C29: 251.46 | D29: 240.88 | E29: 228.38 | F29: 221.3 | H29: 78.65 | I29: 142.65 | J29: 141.63 | K29: 119.4 | L29: 100.48
A30: P/E Ratio | B30: =(B28*B29)/B15 | C30: =(C28*C29)/C15 | D30: =(D28*D29)/D15 | E30: =(E28*E29)/E15 | F30: =(F28*F29)/F15 | H30: =(H28*H29)/H15 | I30: =(I28*I29)/I15 | J30: =(J28*J29)/J15 | K30: =(K28*K29)/K15 | L30: =(L28*L29)/L15

Sheet DuPont
A1: DuPont Analysis - HCL Technologies vs Wipro
B3: HCL Technologies | H3: Wipro
A4: Component | B4: FY2025 | C4: FY2024 | D4: FY2023 | E4: FY2022 | F4: FY2021 | H4: FY2025 | I4: FY2024 | J4: FY2023 | K4: FY2022 | L4: FY2021
A5: Net Profit Margin | B5: =HCL_Data!B86/HCL_Data!B63 | C5: =HCL_Data!C86/HCL_Data!C63 | D5: =HCL_Data!D86/HCL_Data!D63 | E5: =HCL_Data!E86/HCL_Data!E63 | F5: =HCL_Data!F86/HCL_Data!F63 | H5: =Wipro_Data!B86/Wipro_Data!B63 | I5: =Wipro_Data!C86/Wipro_Data!C63 | J5: =Wipro_Data!D86/Wipro_Data!D63 | K5: =Wipro_Data!E86/Wipro_Data!E63 | L5: =Wipro_Data!F86/Wipro_Data!F63
A6: Asset Turnover | B6: =HCL_Data!B63/HCL_Data!B45 | C6: =HCL_Data!C63/HCL_Data!C45 | D6: =HCL_Data!D63/HCL_Data!D45 | E6: =HCL_Data!E63/HCL_Data!E45 | F6: =HCL_Data!F63/HCL_Data!F45 | H6: =Wipro_Data!B63/Wipro_Data!B45 | I6: =Wipro_Data!C63/Wipro_Data!C45 | J6: =Wipro_Data!D63/Wipro_Data!D45 | K6: =Wipro_Data!E63/Wipro_Data!E45 | L6: =Wipro_Data!F63/Wipro_Data!F45
A7: Equity Multiplier | B7: =HCL_Data!B45/HCL_Data!B11 | C7: =HCL_Data!C45/HCL_Data!C11 | D7: =HCL_Data!D45/HCL_Data!D11 | E7: =HCL_Data!E45/HCL_Data!E11 | F7: =HCL_Data!F45/HCL_Data!F11 | H7: =Wipro_Data!B45/Wipro_Data!B11 | I7: =Wipro_Data!C45/Wipro_Data!C11 | J7: =Wipro_Data!D45/Wipro_Data!D11 | K7: =Wipro_Data!E45/Wipro_Data!E11 | L7: =Wipro_Data!F45/Wipro_Data!F11
A9: ROE via DuPont (%) | B9: =B5*B6*B7*100 | C9: =C5*C6*C7*100 | D9: =D5*D6*D7*100 | E9: =E5*E6*E7*100 | F9: =F5*F6*F7*100 | H9: =H5*H6*H7*100 | I9: =I5*I6*I7*100 | J9: =J5*J6*J7*100 | K9: =K5*K6*K7*100 | L9: =L5*L6*L7*100

Sheet CCC
A1: Cash Conversion Cycle - HCL Technologies vs Wipro
B3: HCL Technologies | H3: Wipro
A4: Component (days) | B4: FY2025 | C4: FY2024 | D4: FY2023 | E4: FY2022 | F4: FY2021 | H4: FY2025 | I4: FY2024 | J4: FY2023 | K4: FY2022 | L4: FY2021
A5: Days Inventory Outstanding (DIO) | B5: =(365*(HCL_Data!B39+HCL_Data!C39)/2)/(HCL_Data!B69+HCL_Data!B70+HCL_Data!B71) | C5: =(365*(HCL_Data!C39+HCL_Data!D39)/2)/(HCL_Data!C69+HCL_Data!C70+HCL_Data!C71) | D5: =(365*(HCL_Data!D39+HCL_Data!E39)/2)/(HCL_Data!D69+HCL_Data!D70+HCL_Data!D71) | E5: =(365*(HCL_Data!E39+HCL_Data!F39)/2)/(HCL_Data!E69+HCL_Data!E70+HCL_Data!E71) | F5: =(365*(HCL_Data!F39+91)/2)/(HCL_Data!F69+HCL_Data!F70+HCL_Data!F71) | H5: =(365*(Wipro_Data!B39+Wipro_Data!C39)/2)/(Wipro_Data!B69+Wipro_Data!B70+Wipro_Data!B71) | I5: =(365*(Wipro_Data!C39+Wipro_Data!D39)/2)/(Wipro_Data!C69+Wipro_Data!C70+Wipro_Data!C71) | J5: =(365*(Wipro_Data!D39+Wipro_Data!E39)/2)/(Wipro_Data!D69+Wipro_Data!D70+Wipro_Data!D71) | K5: =(365*(Wipro_Data!E39+Wipro_Data!F39)/2)/(Wipro_Data!E69+Wipro_Data!E70+Wipro_Data!E71) | L5: =(365*(Wipro_Data!F39+Wipro_Data!G39)/2)/(Wipro_Data!F69+Wipro_Data!F70+Wipro_Data!F71)
A6: Days Sales Outstanding (DSO) | B6: =(365*((HCL_Data!B40+HCL_Data!C40)/2))/HCL_Data!B63 | C6: =(365*((HCL_Data!C40+HCL_Data!D40)/2))/HCL_Data!C63 | D6: =(365*((HCL_Data!D40+HCL_Data!E40)/2))/HCL_Data!D63 | E6: =(365*((HCL_Data!E40+HCL_Data!F40)/2))/HCL_Data!E63 | F6: =(365*((HCL_Data!F40+HCL_Data!G40)/2))/HCL_Data!F63 | H6: =(365*((Wipro_Data!B40+Wipro_Data!C40)/2))/Wipro_Data!B63 | I6: =(365*((Wipro_Data!C40+Wipro_Data!D40)/2))/Wipro_Data!C63 | J6: =(365*((Wipro_Data!D40+Wipro_Data!E40)/2))/Wipro_Data!D63 | K6: =(365*((Wipro_Data!E40+Wipro_Data!F40)/2))/Wipro_Data!E63 | L6: =(365*((Wipro_Data!F40+Wipro_Data!G40)/2))/Wipro_Data!F63
A7: Days Payable Outstanding (DPO) | B7: =(365*((HCL_Data!B21+HCL_Data!C21)/2))/(HCL_Data!B69+HCL_Data!B70+HCL_Data!B75) | C7: =(365*((HCL_Data!C21+HCL_Data!D21)/2))/(HCL_Data!C69+HCL_Data!C70+HCL_Data!C75) | D7: =(365*((HCL_Data!D21+HCL_Data!E21)/2))/(HCL_Data!D69+HCL_Data!D70+HCL_Data!D75) | E7: =(365*((HCL_Data!E21+HCL_Data!F21)/2))/(HCL_Data!E69+HCL_Data!E70+HCL_Data!E75) | F7: =(365*((HCL_Data!F21+HCL_Data!G21)/2))/(HCL_Data!F69+HCL_Data!F70+HCL_Data!F75) | H7: =(365*((Wipro_Data!B21+Wipro_Data!C21)/2))/(Wipro_Data!B69+Wipro_Data!B70+Wipro_Data!B75) | I7: =(365*((Wipro_Data!C21+Wipro_Data!D21)/2))/(Wipro_Data!C69+Wipro_Data!C70+Wipro_Data!C75) | J7: =(365*((Wipro_Data!D21+Wipro_Data!E21)/2))/(Wipro_Data!D69+Wipro_Data!D70+Wipro_Data!D75) | K7: =(365*((Wipro_Data!E21+Wipro_Data!F21)/2))/(Wipro_Data!E69+Wipro_Data!E70+Wipro_Data!E75) | L7: =(365*((Wipro_Data!F21+Wipro_Data!G21)/2))/(Wipro_Data!F69+Wipro_Data!F70+Wipro_Data!F75)
A9: Cash Conversion Cycle (CCC) | B9: =B5+B6-B7 | C9: =C5+C6-C7 | D9: =D5+D6-D7 | E9: =E5+E6-E7 | F9: =F5+F6-F7 | H9: =H5+H6-H7 | I9: =I5+I6-I7 | J9: =J5+J6-J7 | K9: =K5+K6-K7 | L9: =L5+L6-L7
